skip_thoughts/__init__.py
skip_thoughts/configuration.py
skip_thoughts/encoder_manager.py
skip_thoughts/evaluate.py
skip_thoughts/skip_thoughts_encoder.py
skip_thoughts/skip_thoughts_model.py
skip_thoughts/skip_thoughts_model_test.py
skip_thoughts/track_perplexity.py
skip_thoughts/train.py
skip_thoughts/vocabulary_expansion.py
skip_thoughts/data/__init__.py
skip_thoughts/data/preprocess_dataset.py
skip_thoughts/data/special_words.py
skip_thoughts/ops/__init__.py
skip_thoughts/ops/gru_cell.py
skip_thoughts/ops/input_ops.py
skip_thoughts-0.1.0.dist-info/LICENSE
skip_thoughts-0.1.0.dist-info/METADATA
skip_thoughts-0.1.0.dist-info/WHEEL
skip_thoughts-0.1.0.dist-info/top_level.txt
skip_thoughts-0.1.0.dist-info/RECORD
