Metadata-Version: 2.1
Name: skip-thoughts
Version: 0.1.0
Summary: A pip installable version of skip_thoughts branched from tensorflow/research
Home-page: https://github.com/RetroRabbit/skip_thoughts
Author: Julien Nyambal
Author-email: jnyambal@retrorabbit.co.za
License: UNKNOWN
Platform: UNKNOWN
Requires-Python: >=2.7
Requires-Dist: six (==1.11.0)
Requires-Dist: tensorflow (==1.9.0)
Requires-Dist: numpy (==1.14.3)
Requires-Dist: nltk (==3.3)
Requires-Dist: gensim (==3.6.0)
Requires-Dist: scikit-learn (==0.19.1)
